clinc/__init__.py
clinc/clinc_util.py
clinc-0.1.2.dist-info/DESCRIPTION.rst
clinc-0.1.2.dist-info/METADATA
clinc-0.1.2.dist-info/RECORD
clinc-0.1.2.dist-info/WHEEL
clinc-0.1.2.dist-info/metadata.json
clinc-0.1.2.dist-info/top_level.txt
