Metadata-Version: 2.0
Name: clinc
Version: 0.1.2
Summary: Cell Lineage from Normalized Covariance 
Home-page: https://github.com/AllonKleinLab/Cell-Lineage-from-Normalized-Covariance
Author: Caleb Weinreb
Author-email: calebsw@gmail.com
License: UNKNOWN
Platform: UNKNOWN
Classifier: Programming Language :: Python :: 3
Classifier: License :: OSI Approved :: MIT License
Classifier: Operating System :: OS Independent
Requires-Python: >=3.6
Requires-Dist: ete3
Requires-Dist: numpy
Requires-Dist: scipy
Requires-Dist: matplotlib
Requires-Dist: ipykernel
Requires-Dist: jupyter
Requires-Dist: fastcluster
Requires-Dist: SetCoverPy
